barrios/__init__.py
barrios/main.py
barrios-0.1.1.dist-info/licenses/LICENCE
barrios-0.1.1.dist-info/METADATA
barrios-0.1.1.dist-info/WHEEL
barrios-0.1.1.dist-info/top_level.txt
barrios-0.1.1.dist-info/RECORD
