Metadata-Version: 2.4
Name: barrios
Version: 0.1.1
Summary: A personal package that serves several purposes, especially in Chile.
Home-page: https://cyax.up.railway.app/
Author: Matias Barrios
Author-email: matias.barrios.wow@gmail.com
License-File: LICENCE
Dynamic: author
Dynamic: author-email
Dynamic: description
Dynamic: description-content-type
Dynamic: home-page
Dynamic: license-file
Dynamic: summary
